networking_baremetal/__init__.py
networking_baremetal/_i18n.py
networking_baremetal/common.py
networking_baremetal/config.py
networking_baremetal/constants.py
networking_baremetal/exceptions.py
networking_baremetal/ironic_client.py
networking_baremetal/agent/__init__.py
networking_baremetal/agent/ironic_neutron_agent.py
networking_baremetal/drivers/__init__.py
networking_baremetal/drivers/base.py
networking_baremetal/drivers/netconf/openconfig.py
networking_baremetal/openconfig/__init__.py
networking_baremetal/openconfig/interfaces/__init__.py
networking_baremetal/openconfig/interfaces/aggregate.py
networking_baremetal/openconfig/interfaces/ethernet.py
networking_baremetal/openconfig/interfaces/interfaces.py
networking_baremetal/openconfig/interfaces/types.py
networking_baremetal/openconfig/lacp/__init__.py
networking_baremetal/openconfig/lacp/lacp.py
networking_baremetal/openconfig/lacp/types.py
networking_baremetal/openconfig/network_instance/__init__.py
networking_baremetal/openconfig/network_instance/network_instance.py
networking_baremetal/openconfig/vlan/__init__.py
networking_baremetal/openconfig/vlan/types.py
networking_baremetal/openconfig/vlan/vlan.py
networking_baremetal/plugins/__init__.py
networking_baremetal/plugins/ml2/__init__.py
networking_baremetal/plugins/ml2/baremetal_mech.py
networking_baremetal/tests/__init__.py
networking_baremetal/tests/base.py
networking_baremetal/tests/unit/__init__.py
networking_baremetal/tests/unit/drivers/__init__.py
networking_baremetal/tests/unit/drivers/netconf/__init__.py
networking_baremetal/tests/unit/drivers/netconf/test_openconfig.py
networking_baremetal/tests/unit/ironic_agent/__init__.py
networking_baremetal/tests/unit/ironic_agent/test_hashring_member_manager.py
networking_baremetal/tests/unit/ironic_agent/test_ironic_agent.py
networking_baremetal/tests/unit/openconfig/__init__.py
networking_baremetal/tests/unit/openconfig/test_interfaces.py
networking_baremetal/tests/unit/openconfig/test_lacp.py
networking_baremetal-7.0.0.dist-info/AUTHORS
networking_baremetal-7.0.0.dist-info/LICENSE
networking_baremetal-7.0.0.dist-info/METADATA
networking_baremetal-7.0.0.dist-info/WHEEL
networking_baremetal-7.0.0.dist-info/entry_points.txt
networking_baremetal-7.0.0.dist-info/pbr.json
networking_baremetal-7.0.0.dist-info/top_level.txt
networking_baremetal-7.0.0.dist-info/RECORD
