Metadata-Version: 2.1
Name: networking-baremetal
Version: 7.0.0
Summary: Neutron plugin that provides deep Ironic/Neutron integration.
Home-page: https://docs.openstack.org/networking-baremetal/latest/
Author: OpenStack
Author-email: openstack-discuss@lists.openstack.org
Classifier: Environment :: OpenStack
Classifier: Intended Audience :: Information Technology
Classifier: Intended Audience :: System Administrators
Classifier: License :: OSI Approved :: Apache Software License
Classifier: Operating System :: POSIX :: Linux
Classifier: Programming Language :: Python
Classifier: Programming Language :: Python :: Implementation :: CPython
Classifier: Programming Language :: Python :: 3 :: Only
Classifier: Programming Language :: Python :: 3
Classifier: Programming Language :: Python :: 3.10
Classifier: Programming Language :: Python :: 3.11
Classifier: Programming Language :: Python :: 3.12
Requires-Python: >=3.10
License-File: LICENSE
License-File: AUTHORS
Requires-Dist: ncclient >=0.6.9
Requires-Dist: neutron-lib >=1.28.0
Requires-Dist: oslo.config >=9.7.1
Requires-Dist: oslo.i18n >=6.5.1
Requires-Dist: oslo.log >=7.1.0
Requires-Dist: oslo.utils >=8.2.0
Requires-Dist: oslo.messaging >=16.1.0
Requires-Dist: oslo.service[threading] >=4.2.0
Requires-Dist: pbr >=6.0.0
Requires-Dist: openstacksdk >=0.31.2
Requires-Dist: tooz >=6.3.0
Requires-Dist: neutron >=14.0.0.0b1
Requires-Dist: tenacity >=6.0.0
Requires-Dist: keystoneauth1 >=3.14.0
